fastapi_rate_limit/__init__.py
fastapi_rate_limit/middleware.py
fastapi_ratelimit_middleware-0.1.0.dist-info/licenses/LICENSE
fastapi_ratelimit_middleware-0.1.0.dist-info/METADATA
fastapi_ratelimit_middleware-0.1.0.dist-info/WHEEL
fastapi_ratelimit_middleware-0.1.0.dist-info/top_level.txt
fastapi_ratelimit_middleware-0.1.0.dist-info/RECORD
